{"duration": 0.1555619239807129, "input_args": {"transformer": "FunctionTransformer(func=<function clean_texts at 0x168400670>)", "X": "17496    here's how a terrorist's son became a peace ac...\n13778    sight of coworkers' stupid fucking faces endur...\n6824     meet the young people trying to make sure detr...\n3062         buck up. the denver holiday season is upon us\n22027    politician spots young female aide, and so it ...\n                               ...                        \n18489    nyc mayor: 'reconcile yourselves with your god...\n23601    republicans have a way out of their health car...\n4077     robert pattinson & fka twigs spend time at cha...\n20546    researchers no closer to understanding what th...\n3519                  senate votes 64-36, not sure on what\nName: headline, Length: 18316, dtype: object", "y": "17496    0\n13778    1\n6824     0\n3062     0\n22027    1\n        ..\n18489    1\n23601    0\n4077     0\n20546    1\n3519     1\nName: is_sarcastic, Length: 18316, dtype: int64", "weight": "None", "message_clsname": "'Pipeline'", "message": "None", "params": "{'fit': {}, 'partial_fit': {}, 'predict': {}, 'predict_proba': {}, 'predict_log_proba': {}, 'decision_function': {}, 'score': {}, 'split': {}, 'transform': {}, 'inverse_transform': {}, 'fit_transform': {}, 'fit_predict': {}}"}, "time": 1744564656.5952058}